simrunes/__init__.py
simrunes/backend.py
simrunes/constants.py
simrunes/core.py
simrunes/models.py
simrunes-1.0.dist-info/METADATA
simrunes-1.0.dist-info/WHEEL
simrunes-1.0.dist-info/entry_points.txt
simrunes-1.0.dist-info/licenses/LICENSE
simrunes-1.0.dist-info/RECORD
